./.python-version
./1373_process.log
./PKG-INFO
./README.md
./categories.json
./expenses.db
./language.json
./main.py
./package_name
./proxy.py
./push_info.json
./pyproject.toml
./server_config.json
./uv.lock
iflow_mcp_expense_tracker-0.1.4.dist-info/METADATA
iflow_mcp_expense_tracker-0.1.4.dist-info/WHEEL
iflow_mcp_expense_tracker-0.1.4.dist-info/entry_points.txt
iflow_mcp_expense_tracker-0.1.4.dist-info/RECORD
