Metadata-Version: 2.4
Name: iflow-mcp-expense-tracker
Version: 0.1.4
Summary: Add your description here
Requires-Python: >=3.11
Requires-Dist: aiosqlite>=0.21.0
Requires-Dist: fastmcp>=2.12.4
